pyVFRendering.cpython-36m-x86_64-linux-gnu.so
pyVFRendering-0.14.0.dist-info/LICENSE
pyVFRendering-0.14.0.dist-info/METADATA
pyVFRendering-0.14.0.dist-info/WHEEL
pyVFRendering-0.14.0.dist-info/top_level.txt
pyVFRendering-0.14.0.dist-info/RECORD
