Metadata-Version: 2.1
Name: pyVFRendering
Version: 0.14.0
Summary: VFRendering python bindings
Home-page: https://github.com/FlorianRhiem/VFRendering
Author: Florian Rhiem
Author-email: f.rhiem@fz-juelich.de
License: UNKNOWN
Platform: UNKNOWN
Requires-Dist: numpy
